.gitignore
LICENSE
README.txt
setup.py
pdcool/__init__.py
pdcool/database.py
pdcool/dataframe.py
pdcool.egg-info/PKG-INFO
pdcool.egg-info/SOURCES.txt
pdcool.egg-info/dependency_links.txt
pdcool.egg-info/requires.txt
pdcool.egg-info/top_level.txt
tests/test_database.py
tests/test_dataframe.py