Metadata-Version: 2.1
Name: pdcool
Version: 1.1.0
Summary: a library for revang developer
Home-page: https://github.com/revang/pdcool
Author: revang
Author-email: revang.alternative@foxmail.com
License: MIT License
Keywords: pdcool
Platform: any
License-File: LICENSE
